frisbee/__init__.py
frisbee/utils.py
frisbee/cli/__init__.py
frisbee/cli/client.py
frisbee/modules/__init__.py
frisbee/modules/base.py
frisbee/modules/bing.py
frisbee-0.0.7.dist-info/LICENSE
frisbee-0.0.7.dist-info/METADATA
frisbee-0.0.7.dist-info/WHEEL
frisbee-0.0.7.dist-info/entry_points.txt
frisbee-0.0.7.dist-info/top_level.txt
frisbee-0.0.7.dist-info/RECORD
