Metadata-Version: 2.1
Name: frisbee
Version: 0.0.7
Summary: Search tool to find email addresses by abusing search
Home-page: https://github.com/9b/frisbee
Author: Brandon Dixon
Author-email: brandon@9bplus.com
License: MIT
Download-URL: https://github.com/9b/frisbee/archive/master.zip
Keywords: emails,leads,search engine,crawler,intel
Platform: UNKNOWN
Classifier: Development Status :: 4 - Beta
Classifier: Intended Audience :: Developers
Classifier: License :: OSI Approved :: MIT License
Classifier: Natural Language :: English
Classifier: Programming Language :: Python
Classifier: Topic :: Software Development :: Libraries
Requires-Dist: beautifulsoup4
Requires-Dist: requests
Requires-Dist: requests-futures
Requires-Dist: namesgenerator
